{
  "languageserver": {
    "ccls": {
      "command": "ccls",
      "filetypes": ["c", "cc", "cpp", "c++", "objc", "objcpp"],
      "rootPatterns": [".ccls", "compile_commands.json", ".git/", ".hg/"],
      "initializationOptions": {
        "cache": {
          "directory": "/tmp/ccls"
        }
      }
    }
  },
  "Lua.workspace.library": {
    "/usr/share/nvim/runtime/lua": true,
    "/usr/share/nvim/runtime/lua/vim": true,
    "/usr/share/nvim/runtime/lua/vim/lsp": true
  },
  "Lua.diagnostics.globals": ["vim"],
  "coc.preferences.formatOnSaveFiletypes": ["c", "c++", "rust"],
  "suggest.noselect": true
}
